intelligence_toolkit/__init__.py
intelligence_toolkit/AI/__init__.py
intelligence_toolkit/AI/base_batch_async.py
intelligence_toolkit/AI/base_chat.py
intelligence_toolkit/AI/base_embedder.py
intelligence_toolkit/AI/classes.py
intelligence_toolkit/AI/client.py
intelligence_toolkit/AI/defaults.py
intelligence_toolkit/AI/local_embedder.py
intelligence_toolkit/AI/metaprompts.py
intelligence_toolkit/AI/openai_configuration.py
intelligence_toolkit/AI/openai_embedder.py
intelligence_toolkit/AI/text_splitter.py
intelligence_toolkit/AI/types.py
intelligence_toolkit/AI/utils.py
intelligence_toolkit/AI/validation_prompt.py
intelligence_toolkit/AI/vector_store.py
intelligence_toolkit/anonymize_case_data/__init__.py
intelligence_toolkit/anonymize_case_data/api.py
intelligence_toolkit/anonymize_case_data/error_report.py
intelligence_toolkit/anonymize_case_data/queries.py
intelligence_toolkit/anonymize_case_data/synthesizability_statistics.py
intelligence_toolkit/anonymize_case_data/visuals.py
intelligence_toolkit/compare_case_groups/__init__.py
intelligence_toolkit/compare_case_groups/api.py
intelligence_toolkit/compare_case_groups/build_dataframes.py
intelligence_toolkit/compare_case_groups/prompts.py
intelligence_toolkit/compare_case_groups/temporal_process.py
intelligence_toolkit/detect_case_patterns/__init__.py
intelligence_toolkit/detect_case_patterns/api.py
intelligence_toolkit/detect_case_patterns/config.py
intelligence_toolkit/detect_case_patterns/detection_functions.py
intelligence_toolkit/detect_case_patterns/graph_functions.py
intelligence_toolkit/detect_case_patterns/model.py
intelligence_toolkit/detect_case_patterns/prompts.py
intelligence_toolkit/detect_case_patterns/record_counter.py
intelligence_toolkit/detect_entity_networks/__init__.py
intelligence_toolkit/detect_entity_networks/api.py
intelligence_toolkit/detect_entity_networks/classes.py
intelligence_toolkit/detect_entity_networks/config.py
intelligence_toolkit/detect_entity_networks/explore_networks.py
intelligence_toolkit-0.1.3.dist-info/METADATA
intelligence_toolkit-0.1.3.dist-info/WHEEL
intelligence_toolkit-0.1.3.dist-info/licenses/LICENSE
intelligence_toolkit-0.1.3.dist-info/RECORD
