Metadata-Version: 2.4
Name: intelligence-toolkit
Version: 0.1.3
Summary: Interactive workflows for generating AI intelligence reports from real-world data sources using GPT models
Project-URL: source, https://github.com/microsoft/intelligence-toolkit
Project-URL: issues, https://github.com/microsoft/intelligence-toolkit/issues
Author-email: Dayenne Souza <ddesouza@microsoft.com>, Ha Trinh <trinhha@microsoft.com>, Darren Edge <daedge@microsoft.com>
License-File: LICENSE
Keywords: AI,data analysis,reports,workflows
Requires-Python: <3.13,>=3.11
Requires-Dist: altair-viewer<1.0.0,>=0.4.0
Requires-Dist: altair==4.2.2
Requires-Dist: azure-core==1.35.1
Requires-Dist: azure-identity==1.17.1
Requires-Dist: duckdb==1.1.0
Requires-Dist: future<2.0.0,>=1.0.0
Requires-Dist: graspologic<4.0.0,>=3.4.1
Requires-Dist: jsonschema<5.0.0,>=4.23.0
Requires-Dist: lancedb==0.12.0
Requires-Dist: markdown2==2.5.4
Requires-Dist: nest-asyncio<2.0.0,>=1.6.0
Requires-Dist: networkx==3.5
Requires-Dist: numpy==1.26.4
Requires-Dist: openai<2.0.0,>=1.37.1
Requires-Dist: pac-synth==0.0.8
Requires-Dist: pdfkit==1.0.0
Requires-Dist: plotly-express==0.4.1
Requires-Dist: plotly==5.22.0
Requires-Dist: poethepoet<1.0.0,>=0.27.0
Requires-Dist: polars==0.20.10
Requires-Dist: pyarrow==15.0.0
Requires-Dist: pydantic-core==2.20.1
Requires-Dist: pydantic==2.8.2
Requires-Dist: pypdf<6.0.0,>=5.1.0
Requires-Dist: scikit-learn==1.5.1
Requires-Dist: scipy==1.12.0
Requires-Dist: seaborn==0.13.2
Requires-Dist: semchunk==2.2.0
Requires-Dist: sentence-transformers<4.0.0,>=3.1.1
Requires-Dist: streamlit-aggrid==0.3.4.post3
Requires-Dist: streamlit-agraph==0.0.45
Requires-Dist: streamlit-javascript==0.1.5
Requires-Dist: streamlit==1.31.1
Requires-Dist: textblob==0.19.0
Requires-Dist: tiktoken==0.7.0
Requires-Dist: torch==2.4.1; sys_platform != 'darwin'
Requires-Dist: torch==2.5.1; sys_platform == 'darwin'
Provides-Extra: dev
Requires-Dist: coverage<8.0.0,>=7.6.0; extra == 'dev'
Requires-Dist: faker<29.0.0,>=28.0.0; extra == 'dev'
Requires-Dist: ipykernel<7.0.0,>=6.29.5; extra == 'dev'
Requires-Dist: nbformat<6.0.0,>=5.10.4; extra == 'dev'
Requires-Dist: pyright<2.0.0,>=1.1.371; extra == 'dev'
Requires-Dist: pytest-asyncio<1.0.0,>=0.23.7; extra == 'dev'
Requires-Dist: pytest-cov<6.0.0,>=5.0.0; extra == 'dev'
Requires-Dist: pytest-mock<4.0.0,>=3.14.0; extra == 'dev'
Requires-Dist: pytest<9.0.0,>=8.2.2; extra == 'dev'
Requires-Dist: ruff<1.0.0,>=0.4.7; extra == 'dev'
